ca_cdk_constructs/__init__.py
ca_cdk_constructs/cross_account_domain_delegation.py
ca_cdk_constructs/ecr/__init__.py
ca_cdk_constructs/ecr/ecr_repository.py
ca_cdk_constructs/edge_services/__init__.py
ca_cdk_constructs/edge_services/waf_rule_templates.py
ca_cdk_constructs/edge_services/waf_v2_builder.py
ca_cdk_constructs/eks/__init__.py
ca_cdk_constructs/eks/eks_cluster_integration.py
ca_cdk_constructs/eks/external_secrets/__init__.py
ca_cdk_constructs/eks/external_secrets/external_aws_secrets_chart.py
ca_cdk_constructs/eks/external_secrets/external_secret.py
ca_cdk_constructs/eks/external_secrets/external_secrets_aws_secret_store.py
ca_cdk_constructs/eks/imports/io/external_secrets/__init__.py
ca_cdk_constructs/eks/imports/io/external_secrets/_jsii/__init__.py
ca_cdk_constructs/eks/imports/io/external_secrets/_jsii/ioexternal-secrets@0.0.0.jsii.tgz
ca_cdk_constructs/eks/imports/io/external_secrets/generators/__init__.py
ca_cdk_constructs/eks/imports/io/external_secrets/generators/_jsii/__init__.py
ca_cdk_constructs/eks/imports/io/external_secrets/generators/_jsii/ioexternal-secretsgenerators@0.0.0.jsii.tgz
ca_cdk_constructs/eks/imports/io/external_secrets/generators/py.typed
ca_cdk_constructs/eks/imports/io/external_secrets/py.typed
ca_cdk_constructs/eks/imports/io/k8s/autoscaling/__init__.py
ca_cdk_constructs/eks/imports/io/k8s/autoscaling/_jsii/__init__.py
ca_cdk_constructs/eks/imports/io/k8s/autoscaling/_jsii/iok8sautoscaling@0.0.0.jsii.tgz
ca_cdk_constructs/eks/imports/io/k8s/autoscaling/py.typed
ca_cdk_constructs/eks/imports/k8s/__init__.py
ca_cdk_constructs/eks/imports/k8s/_jsii/__init__.py
ca_cdk_constructs/eks/imports/k8s/_jsii/k8s@0.0.0.jsii.tgz
ca_cdk_constructs/eks/imports/k8s/py.typed
ca_cdk_constructs/py.typed
ca_cdk_constructs/storage/__init__.py
ca_cdk_constructs/storage/aurora_clone_refresh.py
ca_cdk_constructs/storage/aurora_fast_clone/__init__.py
ca_cdk_constructs/storage/aurora_fast_clone/aurora_check_status.py
ca_cdk_constructs-0.17.2.dist-info/WHEEL
ca_cdk_constructs-0.17.2.dist-info/METADATA
ca_cdk_constructs-0.17.2.dist-info/RECORD
