Metadata-Version: 2.3
Name: ca-cdk-constructs
Version: 0.17.2
Summary: Shared CDK constructs
Author: Citizens Advice
Author-email: Citizens Advice <cloud.engineering@citizensadvice.org.uk>
License:  The MIT License (MIT)
Requires-Dist: aws-cdk-lib>=2.215
Requires-Dist: cdk8s>=2.70.15
Requires-Dist: constructs>=10.4
Requires-Dist: cdk-remote-stack>=2.1
Requires-Dist: aws-cdk-lambda-layer-kubectl-v34>=2.0.0
Requires-Python: >=3.10
Project-URL: Changelog, https://github.com/citizensadvice/ca-cdk-constructs/releases
Project-URL: Homepage, https://github.com/citizensadvice/ca-cdk-constructs
Project-URL: Issues, https://github.com/citizensadvice/ca-cdk-constructs/issues
Project-URL: Repository, https://github.com/matthewcane/ca-cdk-constructs
